Workbook

Sheet Calculadora
A1: Calculadora de Consumo Azure Blob Storage
A2: Cuántos TB corresponden a un presupuesto mensual dado, según tier y redundancia
A4: 1. Datos de entrada (editar celdas amarillas)
A5: Presupuesto mensual objetivo (USD) | B5: 1000
A6: Tier de almacenamiento | B6: Hot
A7: Redundancia | B7: LRS
A8: % del gasto que NO es storage puro (transacciones, egress, otros) | B8: 0
A10: 2. Situación actual del cliente (para comparar)
A11: Gasto total actual (USD/mes) — base + excedente | B11: 1000
A12: TB actuales estimados (según tu cálculo) | B12: 37.5
A14: 3. Resultados
A15: Precio efectivo (USD / GB / mes) | B15: =INDEX('Precios Base'!$C$4:$C$15,MATCH(B6&"-"&B7,'Precios Base'!$E$4:$E$15,0)) -> 0.018
A16: Precio efectivo (USD / TB / mes) | B16: =B15*1024 -> 18.432
A17: Presupuesto disponible solo para storage (USD) | B17: =B5*(1-B8) -> 1000
A18: TB correspondientes al presupuesto | B18: =B17/B16 -> 54.253472
A20: 4. Comparación con el consumo actual
A21: Costo implícito actual (USD / TB) | B21: =B11/B12 -> 26.666667
A22: Diferencia vs. precio efectivo del tier elegido | B22: =B21-B16 -> 8.2346667
A23: Interpretación | B23: =IF(ABS(B22)<2,"Coincide con el tier/redundancia elegido",IF(B22>0,"El costo actual por TB es MAYOR: probablemente hay más redundancia, transacciones/egress, u objetos pequeños facturando de más","El costo actual por TB es MENOR: revisa si el tier/redundancia elegido aquí es el correcto")) -> El costo actual por TB es MAYOR: probablemente hay más redundancia, transacciones/egress, u objetos pequeños facturando de más
A25: Nota: este cálculo es solo de capacidad almacenada (storage). No incluye transacciones (PUT/GET/LIST), egress, ni el mínimo facturable de 128 KiB por objeto en Cool/Cold/Archive. Para un número exacto, cruza esto con el desglose real de Azure Cost Management (Meter Category = Storage).

Sheet Escenarios
A1: Escenarios: TB por presupuesto, todos los tiers y redundancias
A2: El presupuesto y el % no-storage se jalan automáticamente de la hoja Calculadora
A4: Tier | B4: Redundancia | C4: Precio USD/GB | D4: Precio USD/TB | E4: TB por presupuesto
A5: Hot | B5: LRS | C5: =INDEX('Precios Base'!$C$4:$C$15,MATCH(A5&"-"&B5,'Precios Base'!$E$4:$E$15,0)) -> 0.018 | D5: =C5*1024 -> 18.432 | E5: =(Calculadora!$B$5*(1-Calculadora!$B$8))/D5 -> 54.253472
A6: Hot | B6: ZRS | C6: =INDEX('Precios Base'!$C$4:$C$15,MATCH(A6&"-"&B6,'Precios Base'!$E$4:$E$15,0)) -> 0.0225 | D6: =C6*1024 -> 23.04 | E6: =(Calculadora!$B$5*(1-Calculadora!$B$8))/D6 -> 43.402778
A7: Hot | B7: GRS | C7: =INDEX('Precios Base'!$C$4:$C$15,MATCH(A7&"-"&B7,'Precios Base'!$E$4:$E$15,0)) -> 0.036 | D7: =C7*1024 -> 36.864 | E7: =(Calculadora!$B$5*(1-Calculadora!$B$8))/D7 -> 27.126736
A8: Hot | B8: RA-GRS | C8: =INDEX('Precios Base'!$C$4:$C$15,MATCH(A8&"-"&B8,'Precios Base'!$E$4:$E$15,0)) -> 0.045 | D8: =C8*1024 -> 46.08 | E8: =(Calculadora!$B$5*(1-Calculadora!$B$8))/D8 -> 21.701389
A9: Cool | B9: LRS | C9: =INDEX('Precios Base'!$C$4:$C$15,MATCH(A9&"-"&B9,'Precios Base'!$E$4:$E$15,0)) -> 0.01 | D9: =C9*1024 -> 10.24 | E9: =(Calculadora!$B$5*(1-Calculadora!$B$8))/D9 -> 97.65625
A10: Cool | B10: ZRS | C10: =INDEX('Precios Base'!$C$4:$C$15,MATCH(A10&"-"&B10,'Precios Base'!$E$4:$E$15,0)) -> 0.0125 | D10: =C10*1024 -> 12.8 | E10: =(Calculadora!$B$5*(1-Calculadora!$B$8))/D10 -> 78.125
A11: Cool | B11: GRS | C11: =INDEX('Precios Base'!$C$4:$C$15,MATCH(A11&"-"&B11,'Precios Base'!$E$4:$E$15,0)) -> 0.02 | D11: =C11*1024 -> 20.48 | E11: =(Calculadora!$B$5*(1-Calculadora!$B$8))/D11 -> 48.828125
A12: Cool | B12: RA-GRS | C12: =INDEX('Precios Base'!$C$4:$C$15,MATCH(A12&"-"&B12,'Precios Base'!$E$4:$E$15,0)) -> 0.025 | D12: =C12*1024 -> 25.6 | E12: =(Calculadora!$B$5*(1-Calculadora!$B$8))/D12 -> 39.0625
A13: Cold | B13: LRS | C13: =INDEX('Precios Base'!$C$4:$C$15,MATCH(A13&"-"&B13,'Precios Base'!$E$4:$E$15,0)) -> 0.0045 | D13: =C13*1024 -> 4.608 | E13: =(Calculadora!$B$5*(1-Calculadora!$B$8))/D13 -> 217.01389
A14: Cold | B14: GRS | C14: =INDEX('Precios Base'!$C$4:$C$15,MATCH(A14&"-"&B14,'Precios Base'!$E$4:$E$15,0)) -> 0.009 | D14: =C14*1024 -> 9.216 | E14: =(Calculadora!$B$5*(1-Calculadora!$B$8))/D14 -> 108.50694
A15: Archive | B15: LRS | C15: =INDEX('Precios Base'!$C$4:$C$15,MATCH(A15&"-"&B15,'Precios Base'!$E$4:$E$15,0)) -> 0.00099 | D15: =C15*1024 -> 1.01376 | E15: =(Calculadora!$B$5*(1-Calculadora!$B$8))/D15 -> 986.42677
A16: Archive | B16: GRS | C16: =INDEX('Precios Base'!$C$4:$C$15,MATCH(A16&"-"&B16,'Precios Base'!$E$4:$E$15,0)) -> 0.00198 | D16: =C16*1024 -> 2.02752 | E16: =(Calculadora!$B$5*(1-Calculadora!$B$8))/D16 -> 493.21338

Sheet Precios Base
A1: Tabla base de precios — Azure Blob Storage (East US, 2026)
A3: Tier | B3: Redundancia | C3: Precio USD/GB | D3: Multiplicador vs LRS | E3: Clave (uso interno)
A4: Hot | B4: LRS | C4: 0.018 | D4: 1 | E4: =A4&"-"&B4 -> Hot-LRS
A5: Hot | B5: ZRS | C5: 0.0225 | D5: 1.25 | E5: =A5&"-"&B5 -> Hot-ZRS
A6: Hot | B6: GRS | C6: 0.036 | D6: 2 | E6: =A6&"-"&B6 -> Hot-GRS
A7: Hot | B7: RA-GRS | C7: 0.045 | D7: 2.5 | E7: =A7&"-"&B7 -> Hot-RA-GRS
A8: Cool | B8: LRS | C8: 0.01 | D8: 1 | E8: =A8&"-"&B8 -> Cool-LRS
A9: Cool | B9: ZRS | C9: 0.0125 | D9: 1.25 | E9: =A9&"-"&B9 -> Cool-ZRS
A10: Cool | B10: GRS | C10: 0.02 | D10: 2 | E10: =A10&"-"&B10 -> Cool-GRS
A11: Cool | B11: RA-GRS | C11: 0.025 | D11: 2.5 | E11: =A11&"-"&B11 -> Cool-RA-GRS
A12: Cold | B12: LRS | C12: 0.0045 | D12: 1 | E12: =A12&"-"&B12 -> Cold-LRS
A13: Cold | B13: GRS | C13: 0.009 | D13: 2 | E13: =A13&"-"&B13 -> Cold-GRS
A14: Archive | B14: LRS | C14: 0.00099 | D14: 1 | E14: =A14&"-"&B14 -> Archive-LRS
A15: Archive | B15: GRS | C15: 0.00198 | D15: 2 | E15: =A15&"-"&B15 -> Archive-GRS
A17: Notas y supuestos: • Precios de referencia región East US, tier estándar de propósito general v2, según tarifario público de Azure 2026. • 1 TB se calcula como 1,024 GB en todas las fórmulas de este libro. • Cold y Archive solo publican tarifa oficial en LRS; los valores en GRS son una aproximación (2x LRS) siguiendo el mismo patrón que Hot/Cool — verificar en el portal de Azure o la Retail Prices API antes de usarlos en una propuesta formal. • No incluye: transacciones (PUT/GET/LIST/Archive-read), egress, mínimo facturable de 128 KiB por objeto en Cool/Cold/Archive, ni descuentos por Reserved Capacity (hasta 38% en compromisos de 1-3 años). • Fuente: tarifario público Azure Blob Storage 2026 (East US). Re-verificar en portal de Azure antes de decisiones contractuales, ya que Microsoft actualiza precios periódicamente.
