Workbook

Sheet Resumen
A1: Calculadora Azure OpenAI — Plataforma Inteligente
A2: Preparado para Super Naturista
A4: Región de referencia: | B4: US East / East US 2
A5: Fecha de precios: | B5: Junio 2026
A6: Moneda: | B6: USD
A7: Despliegue: | B7: Global Standard PAYG
A8: Fuente: | B8: Precios lista Microsoft Azure (referenciales)
A10: Resumen de Escenarios
A12: Escenario | B12: Descripción | C12: Costo Mensual | D12: Costo Anual | E12: Uso principal | F12: Recomendación
A13: Piloto | B13: Un caso de uso, GPT-4o mini priorizado | C13: =SUMIF(Detalle!H:H,"Sí",Detalle!K:K) -> 289.265 | D13: =C13*12 -> 3471.18 | E13: Validar valor con bajo costo | F13: Iniciar con AI Search Basic
A14: Producción Inicial | B14: 2-3 casos, mezcla GPT-4o y mini | C14: =SUMIF(Detalle!I:I,"Sí",Detalle!L:L) -> 1921.4 | D14: =C14*12 -> 23056.8 | E14: Operación estable | F14: Migrar a AI Search S1
A15: Producción a Escala | B15: Múltiples casos, alta concurrencia | C15: =SUMIF(Detalle!J:J,"Sí",Detalle!M:M) -> 4826.65 | D15: =C15*12 -> 57919.8 | E15: Volumen alto de tokens | F15: Evaluar PTU si >150M tokens/mes
A18: Desglose por Categoría (mensual, USD)
A20: Categoría | B20: Piloto | C20: Producción Inicial | D20: Producción a Escala
A21: Azure OpenAI | B21: =SUMIFS(Detalle!K:K,Detalle!A:A,A21,Detalle!H:H,"Sí") -> 3.215 | C21: =SUMIFS(Detalle!L:L,Detalle!A:A,A21,Detalle!I:I,"Sí") -> 47.15 | D21: =SUMIFS(Detalle!M:M,Detalle!A:A,A21,Detalle!J:J,"Sí") -> 222.4
A22: Azure AI Search | B22: =SUMIFS(Detalle!K:K,Detalle!A:A,A22,Detalle!H:H,"Sí") -> 75 | C22: =SUMIFS(Detalle!L:L,Detalle!A:A,A22,Detalle!I:I,"Sí") -> 250 | D22: =SUMIFS(Detalle!M:M,Detalle!A:A,A22,Detalle!J:J,"Sí") -> 1000
A23: Azure AI Foundry Tools | B23: =SUMIFS(Detalle!K:K,Detalle!A:A,A23,Detalle!H:H,"Sí") -> 5.15 | C23: =SUMIFS(Detalle!L:L,Detalle!A:A,A23,Detalle!I:I,"Sí") -> 50.15 | D23: =SUMIFS(Detalle!M:M,Detalle!A:A,A23,Detalle!J:J,"Sí") -> 500.15
A24: Almacenamiento | B24: =SUMIFS(Detalle!K:K,Detalle!A:A,A24,Detalle!H:H,"Sí") -> 52.9 | C24: =SUMIFS(Detalle!L:L,Detalle!A:A,A24,Detalle!I:I,"Sí") -> 52.9 | D24: =SUMIFS(Detalle!M:M,Detalle!A:A,A24,Detalle!J:J,"Sí") -> 52.9
A25: Cómputo y Web | B25: =SUMIFS(Detalle!K:K,Detalle!A:A,A25,Detalle!H:H,"Sí") -> 95 | C25: =SUMIFS(Detalle!L:L,Detalle!A:A,A25,Detalle!I:I,"Sí") -> 210 | D25: =SUMIFS(Detalle!M:M,Detalle!A:A,A25,Detalle!J:J,"Sí") -> 280
A26: Redes | B26: =SUMIFS(Detalle!K:K,Detalle!A:A,A26,Detalle!H:H,"Sí") -> 0 | C26: =SUMIFS(Detalle!L:L,Detalle!A:A,A26,Detalle!I:I,"Sí") -> 463.2 | D26: =SUMIFS(Detalle!M:M,Detalle!A:A,A26,Detalle!J:J,"Sí") -> 1306.2
A27: Identidad y Seguridad | B27: =SUMIFS(Detalle!K:K,Detalle!A:A,A27,Detalle!H:H,"Sí") -> 25 | C27: =SUMIFS(Detalle!L:L,Detalle!A:A,A27,Detalle!I:I,"Sí") -> 215 | D27: =SUMIFS(Detalle!M:M,Detalle!A:A,A27,Detalle!J:J,"Sí") -> 440
A28: Monitoreo | B28: =SUMIFS(Detalle!K:K,Detalle!A:A,A28,Detalle!H:H,"Sí") -> 33 | C28: =SUMIFS(Detalle!L:L,Detalle!A:A,A28,Detalle!I:I,"Sí") -> 33 | D28: =SUMIFS(Detalle!M:M,Detalle!A:A,A28,Detalle!J:J,"Sí") -> 125
A29: Gobierno | B29: =SUMIFS(Detalle!K:K,Detalle!A:A,A29,Detalle!H:H,"Sí") -> 0 | C29: =SUMIFS(Detalle!L:L,Detalle!A:A,A29,Detalle!I:I,"Sí") -> 500 | D29: =SUMIFS(Detalle!M:M,Detalle!A:A,A29,Detalle!J:J,"Sí") -> 800
A30: Soporte | B30: =SUMIFS(Detalle!K:K,Detalle!A:A,A30,Detalle!H:H,"Sí") -> 0 | C30: =SUMIFS(Detalle!L:L,Detalle!A:A,A30,Detalle!I:I,"Sí") -> 100 | D30: =SUMIFS(Detalle!M:M,Detalle!A:A,A30,Detalle!J:J,"Sí") -> 100
A31: TOTAL | B31: =SUM(B21:B30) -> 289.265 | C31: =SUM(C21:C30) -> 1921.4 | D31: =SUM(D21:D30) -> 4826.65
A34: Notas importantes
A35: • Los precios son referenciales; validar en la calculadora oficial de Azure al momento de la contratación.
A36: • Costos de tokens: para Azure OpenAI, la unidad "Cantidad" en la hoja Detalle representa MILLONES de tokens al mes.
A37: • Los tokens de entrada y salida se listan como componentes separados (input y output tienen tarifas distintas).
A38: • Ajuste las cantidades de tokens según su volumen esperado. Los valores por defecto corresponden a supuestos moderados por escenario.
A39: • Para modificar escenarios: edite las columnas "Cantidad" y "Sí/No" en la hoja "Detalle". Los totales se actualizan automáticamente.
A40: • Para consumo alto sostenido (>150M tokens/mes en GPT-4o), evaluar PTU (Provisioned Throughput Units).

Sheet Detalle
A1: Cálculo Detallado por Componente
A2: Instrucciones: para Azure OpenAI, "Cantidad" = millones de tokens/mes. Ajuste columnas F y H/I/J según cada escenario.
A4: Categoría | B4: Componente | C4: SKU / Configuración | D4: Unidad | E4: Precio Unitario | F4: Cantidad | G4: Costo Mensual | H4: Incluir Piloto | I4: Incluir Prod. Inicial | J4: Incluir Prod. Escala | K4: Costo Piloto | L4: Costo Prod. Inicial | M4: Costo Prod. Escala | N4: Notas
A5: Azure OpenAI | B5: GPT-4o (input tokens) — Piloto | C5: PAYG Global Standard | D5: M tokens/mes | E5: 2.5 | F5: 0.3 | G5: =E5*F5 -> 0.75 | H5: Sí | I5: No | J5: No | K5: =IF(H5="Sí",G5,0) -> 0.75 | L5: =IF(I5="Sí",G5,0) -> 0 | M5: =IF(J5="Sí",G5,0) -> 0 | N5: Piloto: ~300K tokens input al mes en respuestas al usuario.
A6: Azure OpenAI | B6: GPT-4o (input tokens) — Prod. Inicial | C6: PAYG Global Standard | D6: M tokens/mes | E6: 2.5 | F6: 5 | G6: =E6*F6 -> 12.5 | H6: No | I6: Sí | J6: No | K6: =IF(H6="Sí",G6,0) -> 0 | L6: =IF(I6="Sí",G6,0) -> 12.5 | M6: =IF(J6="Sí",G6,0) -> 0 | N6: Prod. inicial: ~5M tokens input/mes.
A7: Azure OpenAI | B7: GPT-4o (input tokens) — Prod. Escala | C7: PAYG Global Standard | D7: M tokens/mes | E7: 2.5 | F7: 25 | G7: =E7*F7 -> 62.5 | H7: No | I7: No | J7: Sí | K7: =IF(H7="Sí",G7,0) -> 0 | L7: =IF(I7="Sí",G7,0) -> 0 | M7: =IF(J7="Sí",G7,0) -> 62.5 | N7: Prod. escala: ~25M tokens input/mes.
A8: Azure OpenAI | B8: GPT-4o (output tokens) — Piloto | C8: PAYG Global Standard | D8: M tokens/mes | E8: 10 | F8: 0.15 | G8: =E8*F8 -> 1.5 | H8: Sí | I8: No | J8: No | K8: =IF(H8="Sí",G8,0) -> 1.5 | L8: =IF(I8="Sí",G8,0) -> 0 | M8: =IF(J8="Sí",G8,0) -> 0 | N8: Salida ~50% del volumen de entrada.
A9: Azure OpenAI | B9: GPT-4o (output tokens) — Prod. Inicial | C9: PAYG Global Standard | D9: M tokens/mes | E9: 10 | F9: 2.5 | G9: =E9*F9 -> 25 | H9: No | I9: Sí | J9: No | K9: =IF(H9="Sí",G9,0) -> 0 | L9: =IF(I9="Sí",G9,0) -> 25 | M9: =IF(J9="Sí",G9,0) -> 0 | N9: Salida ~50% del input.
A10: Azure OpenAI | B10: GPT-4o (output tokens) — Prod. Escala | C10: PAYG Global Standard | D10: M tokens/mes | E10: 10 | F10: 12 | G10: =E10*F10 -> 120 | H10: No | I10: No | J10: Sí | K10: =IF(H10="Sí",G10,0) -> 0 | L10: =IF(I10="Sí",G10,0) -> 0 | M10: =IF(J10="Sí",G10,0) -> 120 | N10: Salida ~50% del input.
A11: Azure OpenAI | B11: GPT-4o mini (input) — Piloto | C11: PAYG Global Standard | D11: M tokens/mes | E11: 0.15 | F11: 2 | G11: =E11*F11 -> 0.3 | H11: Sí | I11: No | J11: No | K11: =IF(H11="Sí",G11,0) -> 0.3 | L11: =IF(I11="Sí",G11,0) -> 0 | M11: =IF(J11="Sí",G11,0) -> 0 | N11: Modelo económico para clasificaciones y extracciones.
A12: Azure OpenAI | B12: GPT-4o mini (input) — Prod. Inicial | C12: PAYG Global Standard | D12: M tokens/mes | E12: 0.15 | F12: 20 | G12: =E12*F12 -> 3 | H12: No | I12: Sí | J12: No | K12: =IF(H12="Sí",G12,0) -> 0 | L12: =IF(I12="Sí",G12,0) -> 3 | M12: =IF(J12="Sí",G12,0) -> 0 | N12: Volumen mayor en tareas rutinarias.
A13: Azure OpenAI | B13: GPT-4o mini (input) — Prod. Escala | C13: PAYG Global Standard | D13: M tokens/mes | E13: 0.15 | F13: 80 | G13: =E13*F13 -> 12 | H13: No | I13: No | J13: Sí | K13: =IF(H13="Sí",G13,0) -> 0 | L13: =IF(I13="Sí",G13,0) -> 0 | M13: =IF(J13="Sí",G13,0) -> 12 | N13: Alto volumen con routing agresivo.
A14: Azure OpenAI | B14: GPT-4o mini (output) — Piloto | C14: PAYG Global Standard | D14: M tokens/mes | E14: 0.6 | F14: 1 | G14: =E14*F14 -> 0.6 | H14: Sí | I14: No | J14: No | K14: =IF(H14="Sí",G14,0) -> 0.6 | L14: =IF(I14="Sí",G14,0) -> 0 | M14: =IF(J14="Sí",G14,0) -> 0 | N14: Salidas cortas en tareas simples.
A15: Azure OpenAI | B15: GPT-4o mini (output) — Prod. Inicial | C15: PAYG Global Standard | D15: M tokens/mes | E15: 0.6 | F15: 10 | G15: =E15*F15 -> 6 | H15: No | I15: Sí | J15: No | K15: =IF(H15="Sí",G15,0) -> 0 | L15: =IF(I15="Sí",G15,0) -> 6 | M15: =IF(J15="Sí",G15,0) -> 0 | N15: Salidas cortas en tareas simples.
A16: Azure OpenAI | B16: GPT-4o mini (output) — Prod. Escala | C16: PAYG Global Standard | D16: M tokens/mes | E16: 0.6 | F16: 40 | G16: =E16*F16 -> 24 | H16: No | I16: No | J16: Sí | K16: =IF(H16="Sí",G16,0) -> 0 | L16: =IF(I16="Sí",G16,0) -> 0 | M16: =IF(J16="Sí",G16,0) -> 24 | N16: Salidas cortas en tareas simples.
... A59: Soporte | B59: Azure Standard Support | C59: Recomendado para producción | D59: Mes | E59: 100 | F59: 1 | G59: =E59*F59 -> 100 | H59: No | I59: Sí | J59: Sí | K59: =IF(H59="Sí",G59,0) -> 0 | L59: =IF(I59="Sí",G59,0) -> 100 | M59: =IF(J59="Sí",G59,0) -> 100 | N59: Soporte estándar. Basic gratis pero limitado.
A60: TOTAL | G60: =SUM(G5:G59) -> 6468.715 | K60: =SUM(K5:K59) -> 289.265 | L60: =SUM(L5:L59) -> 1921.4 | M60: =SUM(M5:M59) -> 4826.65

Sheet Modelos y Precios
A1: Catálogo de Modelos Azure OpenAI y AI Search
A2: Precios PAYG Global Standard (US East 2, junio 2026)
A4: Modelos de Azure OpenAI
A6: Modelo | B6: Entrada / 1M tokens | C6: Salida / 1M tokens | D6: Contexto | E6: Uso principal | F6: Nota
A7: GPT-5.2 | B7: $1.75 | C7: $14.00 | D7: 256K | E7: Razonamiento avanzado | F7: Premium más reciente
A8: GPT-4o | B8: $2.50 | C8: $10.00 | D8: 128K | E8: Motor conversacional | F8: Recomendado para respuestas al usuario
A9: GPT-4o mini | B9: $0.15 | C9: $0.60 | D9: 128K | E9: Clasificación, extracción | F9: Ideal para routing y tareas simples
A10: GPT-4.1 | B10: $3.00 | C10: $12.00 | D10: 1M | E10: Contextos muy largos | F10: Documentos grandes
A11: GPT-4.1 nano | B11: $0.10 | C11: $0.40 | D11: 128K | E11: Alto volumen simple | F11: Costo mínimo
A12: GPT-5 nano | B12: $0.05 | C12: $0.40 | D12: 128K | E12: Ultra económico | F12: Clasificación masiva
A13: o4-mini | B13: $1.21 | C13: $4.84 | D13: 200K | E13: Razonamiento (reasoning) | F13: Problemas complejos
A14: text-embedding-3-large | B14: $0.13 | C14: n/a | D14: 8K | E14: Vectorización de calidad | F14: Recomendado en RAG
A15: text-embedding-3-small | B15: $0.02 | C15: n/a | D15: 8K | E15: Vectorización económica | F15: Alto volumen
A18: Tiers de Azure AI Search
A20: Tier | B20: Precio mensual | C20: Almacenamiento | D20: Réplicas / Particiones | E20: Uso típico | F20: Nota
A21: Free | B21: $0 | C21: 50 MB | D21: 1 / 1 (compartido) | E21: Demos y tutoriales | F21: Solo 1 servicio por suscripción
A22: Basic | B22: ~$75 | C22: 15 GB | D22: Hasta 3 / 3 | E22: Piloto y proyectos pequeños | F22: Recomendado para el piloto
A23: Standard S1 | B23: ~$250 | C23: 160 GB por SU | D23: Hasta 12 / 12 | E23: Producción PyME | F23: Punto de inicio productivo
A24: Standard S2 | B24: ~$1,000 | C24: 2 TB por SU | D24: Hasta 12 / 12 | E24: Volumen alto de datos | F24: Escala mayor
A25: Standard S3 | B25: ~$1,000+/SU | C25: 2-12 TB | D25: Hasta 12 / 12 | E25: Enterprise | F25: Alta concurrencia
A28: Modalidades de Despliegue
A30: Modalidad | B30: Precio base | C30: Break-even | D30: Latencia | E30: Residencia | F30: Recomendación
A31: Global Standard PAYG | B31: Por token | C31: Bajo volumen | D31: Variable (buena) | E31: Sin garantía regional | F31: Piloto y producción inicial
A32: Data Zone (US, EU) | B32: +5-10% | C32: Bajo volumen | D32: Variable | E32: Zona (US o EU) | F32: Cumplimiento regional básico
A33: Regional Standard | B33: +5-10% | C33: Bajo volumen | D33: Baja regional | E33: Región específica | F33: GDPR, FedRAMP
A34: PTU Global | B34: ~$2,448/PTU/mes | C34: 150-200M tokens/mes | D34: Predecible | E34: Sin garantía | F34: Escala sostenida
A35: PTU Reservado 1 año | B35: ~40% descuento | C35: Uso consistente | D35: Predecible | E35: Sin garantía | F35: Cargas estables anuales

Sheet Estimador de Tokens
A1: Estimador de Consumo de Tokens
A2: Herramienta interactiva para dimensionar el consumo mensual esperado y su costo.
A4: Parámetros de uso (ajustables)
A6: Consultas al asistente por día: | B6: 50 | C6: Interacciones únicas al chat.
A7: Días activos por mes: | B7: 22 | C7: Días laborales típicos.
A8: Tokens de entrada promedio por consulta: | B8: 3000 | C8: Prompt sistema + contexto RAG + historia + pregunta.
A9: Tokens de salida promedio por consulta: | B9: 500 | C9: Respuesta narrativa promedio.
A10: Porcentaje enviado a GPT-4o (vs mini): | B10: 0.4 | C10: Rest goes to GPT-4o mini via routing (40% GPT-4o).
A11: Documentos vectorizados al mes: | B11: 100 | C11: Nuevos documentos que se indexan mensualmente.
A12: Tokens promedio por documento: | B12: 5000 | C12: Contenido de un documento típico.
A15: Volumen mensual derivado
A17: Consultas totales al mes: | B17: =B6*B7 -> 1100
A18: Tokens de entrada totales al mes: | B18: =B17*B8 -> 3300000
A19: Tokens de salida totales al mes: | B19: =B17*B9 -> 550000
A20: Tokens entrada GPT-4o (millones): | B20: =B18*B10/1000000 -> 1.32
A21: Tokens entrada GPT-4o mini (millones): | B21: =B18*(1-B10)/1000000 -> 1.98
A22: Tokens salida GPT-4o (millones): | B22: =B19*B10/1000000 -> 0.22
A23: Tokens salida GPT-4o mini (millones): | B23: =B19*(1-B10)/1000000 -> 0.33
A24: Tokens embeddings al mes (millones): | B24: =B11*B12/1000000 -> 0.5
A27: Costo estimado mensual (solo tokens)
A29: Concepto | B29: Millones tokens | C29: Precio /1M | D29: Costo mensual
A30: GPT-4o input | B30: =B20 -> 1.32 | C30: 2.5 | D30: =B30*C30 -> 3.3
A31: GPT-4o output | B31: =B22 -> 0.22 | C31: 10 | D31: =B31*C31 -> 2.2
A32: GPT-4o mini input | B32: =B21 -> 1.98 | C32: 0.15 | D32: =B32*C32 -> 0.297
A33: GPT-4o mini output | B33: =B23 -> 0.33 | C33: 0.6 | D33: =B33*C33 -> 0.198
A34: text-embedding-3-large | B34: =B24 -> 0.5 | C34: 0.13 | D34: =B34*C34 -> 0.065
A35: TOTAL TOKENS | D35: =SUM(D30:D34) -> 6.06
A38: Notas
A39: • Ajuste los parámetros amarillos en las celdas B6:B12 para modelar su volumen esperado.
A40: • Los resultados calculados son SOLO el costo de tokens de Azure OpenAI. NO incluyen AI Search, storage, compute u otros servicios.
A41: • Para el costo total, consulte la hoja "Resumen" y "Detalle".
A42: • Un prompt de sistema típico bien diseñado tiene 500-1,500 tokens; el contexto RAG añade 1,000-3,000 tokens.
A43: • Un token equivale aproximadamente a 4 caracteres o 0.75 palabras en español.

Sheet Notas y Supuestos
A1: Notas, Supuestos y Consideraciones
A3: Origen y vigencia de precios
A4: Precios referenciales de lista pública de Microsoft Azure, junio 2026, despliegue Global Standard PAYG.
A5: Los precios pueden variar ±5-15% dependiendo de la región Azure seleccionada.
A6: Data Zone y Regional Standard aplican un uplift de 5-10% sobre Global Standard.
A7: Validar precios en la calculadora oficial de Azure al momento de la contratación.
A9: Códigos de color
A10: Amarillo claro: celdas de entrada modificables (Cantidad, Sí/No, parámetros).
A11: Púrpura claro: categoría Azure OpenAI (núcleo de la solución).
A12: Verde claro: otras categorías de servicios.
A13: Amarillo intenso: totales calculados.
A14: Azul: encabezados de columna. Azul en texto: valores de entrada. Negro en texto: fórmulas.
... A49: 5. Antes de contratar, valide precios en la calculadora oficial de Azure para la región y fecha correspondientes.
