Workbook

Sheet Resumen
A1: Calculadora Azure — Data Lake con Microsoft Fabric
A2: Preparado para Super Naturista
A4: Región de referencia: | B4: US East
A5: Fecha de precios: | B5: Junio 2026
A6: Moneda: | B6: USD
A7: Fuente: | B7: Precios lista Microsoft Azure (referenciales)
A10: Resumen de Escenarios
A12: Escenario | B12: Descripción | C12: Costo Mensual | D12: Costo Anual | E12: Uso principal | F12: Recomendación
A13: Piloto | B13: Demo y validación (3-6 meses) | C13: =SUMIF(Detalle!H:H,"Sí",Detalle!K:K) -> 439.5 | D13: =C13*12 -> 5274 | E13: Demostrar valor con bajo costo | F13: Iniciar con trial 60 días
A14: Producción Inicial | B14: Operación estable (25 usuarios) | C14: =SUMIF(Detalle!I:I,"Sí",Detalle!L:L) -> 1985.9 | D14: =C14*12 -> 23830.8 | E14: Fase productiva ligera | F14: Reserved 1 año
A15: Producción a Escala | B15: Escalamiento (>80 usuarios) | C15: =SUMIF(Detalle!J:J,"Sí",Detalle!M:M) -> 8150.9 | D15: =C15*12 -> 97810.8 | E15: F64+, libera Pro consumidores | F15: Evaluar F64 reserved
A18: Desglose por Categoría (mensual, USD)
A20: Categoría | B20: Piloto | C20: Producción Inicial | D20: Producción a Escala
A21: Cómputo Fabric | B21: =SUMIFS(Detalle!K:K,Detalle!A:A,A21,Detalle!H:H,"Sí") -> 131.5 | C21: =SUMIFS(Detalle!L:L,Detalle!A:A,A21,Detalle!I:I,"Sí") -> 312 | D21: =SUMIFS(Detalle!M:M,Detalle!A:A,A21,Detalle!J:J,"Sí") -> 4989
A22: Licencias Power BI | B22: =SUMIFS(Detalle!K:K,Detalle!A:A,A22,Detalle!H:H,"Sí") -> 250 | C22: =SUMIFS(Detalle!L:L,Detalle!A:A,A22,Detalle!I:I,"Sí") -> 250 | D22: =SUMIFS(Detalle!M:M,Detalle!A:A,A22,Detalle!J:J,"Sí") -> 50
A23: Redes | B23: =SUMIFS(Detalle!K:K,Detalle!A:A,A23,Detalle!H:H,"Sí") -> 0 | C23: =SUMIFS(Detalle!L:L,Detalle!A:A,A23,Detalle!I:I,"Sí") -> 595.9 | D23: =SUMIFS(Detalle!M:M,Detalle!A:A,A23,Detalle!J:J,"Sí") -> 1688.9
A24: Identidad y Accesos | B24: =SUMIFS(Detalle!K:K,Detalle!A:A,A24,Detalle!H:H,"Sí") -> 0 | C24: =SUMIFS(Detalle!L:L,Detalle!A:A,A24,Detalle!I:I,"Sí") -> 150 | D24: =SUMIFS(Detalle!M:M,Detalle!A:A,A24,Detalle!J:J,"Sí") -> 225
A25: Seguridad | B25: =SUMIFS(Detalle!K:K,Detalle!A:A,A25,Detalle!H:H,"Sí") -> 25 | C25: =SUMIFS(Detalle!L:L,Detalle!A:A,A25,Detalle!I:I,"Sí") -> 65 | D25: =SUMIFS(Detalle!M:M,Detalle!A:A,A25,Detalle!J:J,"Sí") -> 215
A26: Monitoreo | B26: =SUMIFS(Detalle!K:K,Detalle!A:A,A26,Detalle!H:H,"Sí") -> 33 | C26: =SUMIFS(Detalle!L:L,Detalle!A:A,A26,Detalle!I:I,"Sí") -> 33 | D26: =SUMIFS(Detalle!M:M,Detalle!A:A,A26,Detalle!J:J,"Sí") -> 103
A27: Respaldos | B27: =SUMIFS(Detalle!K:K,Detalle!A:A,A27,Detalle!H:H,"Sí") -> 0 | C27: =SUMIFS(Detalle!L:L,Detalle!A:A,A27,Detalle!I:I,"Sí") -> 80 | D27: =SUMIFS(Detalle!M:M,Detalle!A:A,A27,Detalle!J:J,"Sí") -> 80
A28: Gobierno de Datos | B28: =SUMIFS(Detalle!K:K,Detalle!A:A,A28,Detalle!H:H,"Sí") -> 0 | C28: =SUMIFS(Detalle!L:L,Detalle!A:A,A28,Detalle!I:I,"Sí") -> 500 | D28: =SUMIFS(Detalle!M:M,Detalle!A:A,A28,Detalle!J:J,"Sí") -> 800
A29: TOTAL | B29: =SUM(B21:B28) -> 439.5 | C29: =SUM(C21:C28) -> 1985.9 | D29: =SUM(D21:D28) -> 8150.9
A32: Notas importantes
A33: • Los precios son referenciales de lista pública de Microsoft Azure (US East, junio 2026) y deben validarse en el momento de la contratación.
A34: • Para una cotización oficial, utilice la calculadora de Azure: https://azure.microsoft.com/pricing/calculator/
A35: • Los precios pueden variar ±10-15% según la región Azure (Mexico Central, South Central US, etc.).
A36: • Las licencias adquiridas mediante Enterprise Agreement, CSP o Reservado pueden tener descuentos adicionales.
A37: • Este documento no incluye honorarios de servicios profesionales, que se cotizan por separado.
A38: • Para modificar escenarios: edite las columnas "Incluir en..." en la hoja "Detalle" (Sí/No) o ajuste cantidades.

Sheet Detalle
A1: Cálculo Detallado por Componente
A2: Instrucciones: modifique las columnas F (Cantidad) y H/I/J (Sí/No) para ajustar cada escenario.
A4: Categoría | B4: Componente | C4: SKU / Configuración | D4: Unidad | E4: Precio Unitario | F4: Cantidad | G4: Costo Mensual | H4: Incluir Piloto | I4: Incluir Prod. Inicial | J4: Incluir Prod. Escala | K4: Costo Piloto | L4: Costo Prod. Inicial | M4: Costo Prod. Escala | N4: Notas
A5: Cómputo Fabric | B5: Microsoft Fabric F2 | C5: PAYG con pausa 50% | D5: Mes | E5: 131.5 | F5: 1 | G5: =E5*F5 -> 131.5 | H5: Sí | I5: No | J5: No | K5: =IF(H5="Sí",G5,0) -> 131.5 | L5: =IF(I5="Sí",G5,0) -> 0 | M5: =IF(J5="Sí",G5,0) -> 0 | N5: Trial gratis 60 días. Con pausa fuera de horario ahorra ~50%.
A6: Cómputo Fabric | B6: Microsoft Fabric F4 | C6: Reservado 1 año | D6: Mes | E6: 312 | F6: 1 | G6: =E6*F6 -> 312 | H6: No | I6: Sí | J6: No | K6: =IF(H6="Sí",G6,0) -> 0 | L6: =IF(I6="Sí",G6,0) -> 312 | M6: =IF(J6="Sí",G6,0) -> 0 | N6: ~40% descuento vs PAYG. Recomendado post-piloto.
A7: Cómputo Fabric | B7: Microsoft Fabric F64 | C7: Reservado 1 año | D7: Mes | E7: 4989 | F7: 1 | G7: =E7*F7 -> 4989 | H7: No | I7: No | J7: Sí | K7: =IF(H7="Sí",G7,0) -> 0 | L7: =IF(I7="Sí",G7,0) -> 0 | M7: =IF(J7="Sí",G7,0) -> 4989 | N7: Umbral para consumidores Power BI sin licencia Pro.
A8: Licencias Power BI | B8: Power BI Pro — Autores | C8: Licencia por usuario | D8: Usuario/mes | E8: 10 | F8: 5 | G8: =E8*F8 -> 50 | H8: Sí | I8: Sí | J8: Sí | K8: =IF(H8="Sí",G8,0) -> 50 | L8: =IF(I8="Sí",G8,0) -> 50 | M8: =IF(J8="Sí",G8,0) -> 50 | N8: Requerido siempre para quienes crean/publican contenido.
A9: Licencias Power BI | B9: Power BI Pro — Consumidores | C9: Licencia por usuario | D9: Usuario/mes | E9: 10 | F9: 20 | G9: =E9*F9 -> 200 | H9: Sí | I9: Sí | J9: No | K9: =IF(H9="Sí",G9,0) -> 200 | L9: =IF(I9="Sí",G9,0) -> 200 | M9: =IF(J9="Sí",G9,0) -> 0 | N9: No requerido si la capacidad es F64+ (viewers gratis).
A10: Redes | B10: Virtual Network (VNet) | C10: Hub-and-Spoke con subredes | D10: Mes | E10: 0 | F10: 1 | G10: =E10*F10 -> 0 | H10: Sí | I10: Sí | J10: Sí | K10: =IF(H10="Sí",G10,0) -> 0 | L10: =IF(I10="Sí",G10,0) -> 0 | M10: =IF(J10="Sí",G10,0) -> 0 | N10: Servicio gratuito. Aplican cargos por egress de datos.
A11: Redes | B11: Network Security Groups (NSG) | C11: Reglas por subred | D11: Mes | E11: 0 | F11: 1 | G11: =E11*F11 -> 0 | H11: Sí | I11: Sí | J11: Sí | K11: =IF(H11="Sí",G11,0) -> 0 | L11: =IF(I11="Sí",G11,0) -> 0 | M11: =IF(J11="Sí",G11,0) -> 0 | N11: Servicio gratuito. Primera línea de defensa.
A12: Redes | B12: VPN Gateway VpnGw1 | C12: Site-to-Site VPN, 650 Mbps | D12: Mes | E12: 138.7 | F12: 1 | G12: =E12*F12 -> 138.7 | H12: No | I12: Sí | J12: No | K12: =IF(H12="Sí",G12,0) -> 0 | L12: =IF(I12="Sí",G12,0) -> 138.7 | M12: =IF(J12="Sí",G12,0) -> 0 | N12: Para conectar red on-premise con Azure.
A13: Redes | B13: VPN Gateway VpnGw2 | C13: Site-to-Site VPN, 1 Gbps | D13: Mes | E13: 357.7 | F13: 1 | G13: =E13*F13 -> 357.7 | H13: No | I13: No | J13: Sí | K13: =IF(H13="Sí",G13,0) -> 0 | L13: =IF(I13="Sí",G13,0) -> 0 | M13: =IF(J13="Sí",G13,0) -> 357.7 | N13: Para mayor throughput y HA. Sustituye VpnGw1 en escala.
A14: Redes | B14: Private Endpoint | C14: Conexión privada a servicios PaaS | D14: Endpoint/mes | E14: 7.3 | F14: 4 | G14: =E14*F14 -> 29.2 | H14: No | I14: Sí | J14: Sí | K14: =IF(H14="Sí",G14,0) -> 0 | L14: =IF(I14="Sí",G14,0) -> 29.2 | M14: =IF(J14="Sí",G14,0) -> 29.2 | N14: Recomendado para OneLake, Key Vault, SQL. 3-6 endpoints típicos.
A15: Redes | B15: Azure Firewall Basic | C15: Firewall administrado | D15: Mes | E15: 288 | F15: 1 | G15: =E15*F15 -> 288 | H15: No | I15: Sí | J15: No | K15: =IF(H15="Sí",G15,0) -> 0 | L15: =IF(I15="Sí",G15,0) -> 288 | M15: =IF(J15="Sí",G15,0) -> 0 | N15: $0.395/hr. Adecuado para PyMEs. + $0.065/GB procesado.
A16: Redes | B16: Azure Firewall Standard | C16: Firewall administrado avanzado | D16: Mes | E16: 912 | F16: 1 | G16: =E16*F16 -> 912 | H16: No | I16: No | J16: Sí | K16: =IF(H16="Sí",G16,0) -> 0 | L16: =IF(I16="Sí",G16,0) -> 0 | M16: =IF(J16="Sí",G16,0) -> 912 | N16: $1.25/hr. + $0.016/GB procesado. Threat Intel incluido.
... A39: Gobierno de Datos | B39: Azure Cost Management | C39: Control de gastos y budgets | D39: Mes | E39: 0 | F39: 1 | G39: =E39*F39 -> 0 | H39: Sí | I39: Sí | J39: Sí | K39: =IF(H39="Sí",G39,0) -> 0 | L39: =IF(I39="Sí",G39,0) -> 0 | M39: =IF(J39="Sí",G39,0) -> 0 | N39: Servicio gratuito. Configurar budgets y alertas de costo.
A40: TOTAL | G40: =SUM(G5:G39) -> 9871.1 | K40: =SUM(K5:K39) -> 439.5 | L40: =SUM(L5:L39) -> 1985.9 | M40: =SUM(M5:M39) -> 8150.9

Sheet SKUs Fabric
A1: Catálogo de SKUs — Microsoft Fabric
A2: Referencia de precios PAYG y Reservado 1 año (US East, junio 2026)
A4: SKU | B4: CUs | C4: PAYG (USD/mes) | D4: Reservado 1 año (USD/mes) | E4: Almacenamiento Mirroring gratuito | F4: Uso típico
A5: F2 | B5: 2 | C5: 263 | D5: 156 | E5: 2 TB | F5: Piloto / Demo
A6: F4 | B6: 4 | C6: 526 | D6: 312 | E6: 4 TB | F6: Equipos pequeños
A7: F8 | B7: 8 | C7: 1051 | D7: 623 | E7: 8 TB | F7: Producción ligera
A8: F16 | B8: 16 | C8: 2102 | D8: 1247 | E8: 16 TB | F8: Cargas medianas
A9: F32 | B9: 32 | C9: 4205 | D9: 2494 | E9: 32 TB | F9: Mediana empresa
A10: F64 | B10: 64 | C10: 8410 | D10: 4989 | E10: 64 TB | F10: Umbral free viewers
A11: F128 | B11: 128 | C11: 16820 | D11: 9977 | E11: 128 TB | F11: Alta concurrencia
A12: F256 | B12: 256 | C12: 33640 | D12: 19954 | E12: 256 TB | F12: Enterprise
A15: Notas sobre licenciamiento
A16: • F64 es el umbral crítico: por debajo, todos los consumidores de reportes Power BI requieren licencia Pro (~$10 USD/usuario/mes).
A17: • A partir de F64, los consumidores no requieren Pro; solo los autores.
A18: • Reservado a 1 año ofrece ~40% descuento sobre PAYG. Reservado a 3 años ofrece ~50%.
A19: • PAYG permite pausar la capacidad; ideal para pilotos con uso no continuo.
A20: • Cada SKU incluye almacenamiento gratuito de Mirroring hasta el tamaño mostrado.
A21: • Consulte la calculadora oficial: https://azure.microsoft.com/pricing/calculator/

Sheet Notas y Supuestos
A1: Notas, Supuestos y Consideraciones
A3: Origen y vigencia de precios
A4: Los precios listados corresponden a lista pública de Microsoft Azure en región US East, con referencia a junio de 2026.
A5: Los precios pueden variar hasta ±10-15% dependiendo de la región Azure seleccionada (Mexico Central, South Central US, East US 2, etc.).
A6: Los precios oficiales deben validarse en el momento de la contratación mediante la calculadora oficial de Azure.
A7: Precios de licencias por usuario (Power BI Pro, Entra ID) no incluyen descuentos por Enterprise Agreement, CSP o volumen.
A9: Códigos de color de la calculadora
A10: Amarillo claro: celdas de entrada modificables por el usuario (cantidades, Sí/No).
A11: Verde claro: filas de inicio de categoría (encabezado de categoría).
A12: Amarillo intenso: totales calculados.
A13: Azul: encabezados de columnas.
A14: Texto en color azul: valores de entrada del usuario. Texto en negro: fórmulas calculadas.
... A42: Configurar budgets y alertas de costo en Azure Cost Management desde el día uno.
