Workbook

Sheet Supuestos y Dimensionamiento
A1: Azure Event Hubs – Calculadora de Propuesta de Servicios
A2: Nivel: Standard | Región: East US | Moneda: USD
A4: A. PARÁMETROS DE ENTRADA (valores en azul = editables)
A5: Parámetro | B5: Valor | C5: Unidad | D5: Notas
A6: Eventos por segundo (EPS) – promedio | B6: 5000 | C6: EPS | D6: Rango seleccionado: 1,000-10,000 EPS
A7: Eventos por segundo (EPS) – pico | B7: 8000 | C7: EPS | D7: Estimado al 160% del promedio
A8: Tamaño promedio de evento | B8: 5 | C8: KB | D8: Rango seleccionado: 1-10 KB
A9: Días de retención de datos | B9: 7 | C9: días | D9: Máximo en nivel Standard
A10: Consumer Groups | B10: 8 | C10: CGs | D10: Rango seleccionado: 6-10
A11: Horas de operación al día | B11: 24 | C11: hrs | D11: Operación continua 24/7
A12: Días al mes | B12: 30 | C12: días | D12: Mes estándar de facturación Azure
A15: B. CÁLCULO DE THROUGHPUT Y THROUGHPUT UNITS (TUs)
A16: Métrica | B16: Valor | C16: Unidad | D16: Fórmula / Fuente
A17: Throughput de ingesta promedio (MB/s) | B17: =B6*B8/1024 -> 24.414062 | C17: MB/s | D17: EPS × Tamaño_KB ÷ 1024
A18: Throughput de ingesta en pico (MB/s) | B18: =B7*B8/1024 -> 39.0625 | C18: MB/s | D18: EPS_pico × Tamaño_KB ÷ 1024
A19: TUs requeridas por ingesta (pico) | B19: =CEILING(B18/1,1) -> 40 | C19: TUs | D19: Cada TU = 1 MB/s ingesta; CEILING al entero
A20: TUs requeridas por egreso (pico) | B20: =CEILING(B18*B10/2,1) -> 157 | C20: TUs | D20: Egreso = 2 MB/s/TU; ×CGs con factor 0.5
A21: TUs requeridas (máximo) | B21: =MAX(B19,B20) -> 157 | C21: TUs | D21: Máximo entre ingesta y egreso
A22: TUs recomendadas (buffer +20%) | B22: =CEILING(B21*1.2,1) -> 189 | C22: TUs | D22: Margen de seguridad 20%
A23: Particiones recomendadas | B23: =MAX(B22*2, B10*2) -> 378 | C23: particiones | D23: 2× TUs o 2× CGs; mín 32
A26: C. ESTIMACIÓN DE ALMACENAMIENTO (Retención 7 días)
A27: Métrica | B27: Valor | C27: Unidad | D27: Fórmula
A28: Datos ingestados por hora (GB) | B28: =B6*B8*3600/1024/1024 -> 85.830688 | C28: GB/hr | D28: EPS × KB × 3600 seg ÷ 1024²
A29: Datos ingestados por día (GB) | B29: =B28*B11 -> 2059.9365 | C29: GB/día | D29: GB_hr × Horas
A30: Datos ingestados por mes (GB) | B30: =B29*B12 -> 61798.096 | C30: GB/mes | D30: GB_día × Días
A31: Almacenamiento total retenido (TB) | B31: =B29*B9/1024 -> 14.081597 | C31: TB | D31: GB_día × Días_retención ÷ 1024
A32: Almacenamiento total retenido (GB) | B32: =B29*B9 -> 14419.556 | C32: GB | D32: GB_día × Días_retención
A35: D. VOLUMEN DE EVENTOS MENSUAL
A36: Métrica | B36: Valor | C36: Unidad | D36: Fórmula
A37: Eventos por hora | B37: =B6*3600 -> 18000000 | C37: eventos/hr | D37: EPS × 3600
A38: Eventos por día | B38: =B37*B11 -> 432000000 | C38: eventos/día
A39: Eventos por mes | B39: =B38*B12 -> 12960000000 | C39: eventos/mes
A40: Eventos por mes (millones) | B40: =B39/1000000 -> 12960 | C40: M eventos | D40: Referencia para facturación
A41: Unidades de 1M eventos al mes | B41: =CEILING(B40,1) -> 12960 | C41: unidades | D41: Azure factura por millones de eventos en Basic/Standard

Sheet Costos Mensuales
A1: Azure Event Hubs – Desglose de Costos Mensuales (Standard)
A2: Precios de referencia: Azure Pricing (East US, March 2026) – sujeto a cambio
A4: PRECIOS UNITARIOS DE REFERENCIA (Standard – East US)
A5: Componente | B5: Precio Unit. | C5: Unidad | D5: Aplicable | E5: Fuente
A6: Throughput Unit (TU) – por hora | B6: 0.03 | C6: USD/TU/hr | D6: Sí | E6: azure.microsoft.com/pricing/details/event-hubs
A7: Eventos de ingesta (primeros 1M incl.) | B7: 0.028 | C7: USD/millón | D7: Sí | E7: Sobre el primer millón incluido por TU
A8: Retención extendida (días 2-7) | B8: 0.01 | C8: USD/GB/día | D8: Sí | E8: Días 2 en adelante; día 1 gratis
A9: Event Hubs Capture (opcional) | B9: 0.148 | C9: USD/hr/namespace | D9: No | E9: Si se requiere captura a Blob/ADLS
A10: Consumer Groups adicionales (>1) | B10: 0 | C10: USD | D10: — | E10: Incluidos hasta 20 en Standard
A13: CÁLCULO DE COSTOS MENSUALES
A14: Componente | B14: Cantidad | C14: Precio Unit. | D14: Costo Mensual | E14: Notas
A15: Throughput Units (TUs) | B15: ='Supuestos y Dimensionamiento'!B22 -> 189 | C15: =B6 -> 0.03 | D15: =B15*C15*24*'Supuestos y Dimensionamiento'!B12 -> 4082.4 | E15: TUs × $0.03/hr × 24hr × 30 días
A16: Eventos de ingesta adicionales (sobre 1M incluido) | B16: =MAX('Supuestos y Dimensionamiento'!B41-'Supuestos y Dimensionamiento'!B22,0) -> 12771 | C16: =B7 -> 0.028 | D16: =B16*C16 -> 357.588 | E16: Millones adicionales × $0.028
A17: Retención extendida días 2-7 (6 días pagados) | B17: ='Supuestos y Dimensionamiento'!B29 -> 2059.9365 | C17: =B8*6 -> 0.06 | D17: =B17*B8*6 -> 123.59619 | E17: GB/día × $0.01/GB × 6 días pagados
A18: Consumer Groups (incluidos en Standard) | B18: ='Supuestos y Dimensionamiento'!B10 -> 8 | C18: 0 | D18: =0 -> 0 | E18: Hasta 20 CGs incluidos en Standard
A19: SUBTOTAL MENSUAL (sin Capture) | D19: =SUM(D15:D18) -> 4563.5842
A20: Buffer de contingencia (10%) | B20: 10% | D20: =D19*0.1 -> 456.35842 | E20: Recomendado para propuestas comerciales
A21: COSTO TOTAL MENSUAL ESTIMADO | D21: =D19+D20 -> 5019.9426 | E21: Incluye buffer de contingencia
A22: Proyección anual (×12) | D22: =D21*12 -> 60239.311

Sheet Resumen Ejecutivo
A1: Azure Event Hubs – Resumen Ejecutivo de Propuesta
A3: ARQUITECTURA RECOMENDADA
A4: Nivel / SKU | B4: Standard
A5: Throughput Units | B5: ='Supuestos y Dimensionamiento'!B22 & " TUs (recomendadas)" -> 189 TUs (recomendadas)
A6: Particiones | B6: ='Supuestos y Dimensionamiento'!B23 & " particiones" -> 378 particiones
A7: Consumer Groups | B7: ='Supuestos y Dimensionamiento'!B10 & " CGs" -> 8 CGs
A8: Retención de datos | B8: ='Supuestos y Dimensionamiento'!B9 & " días" -> 7 días
A9: Región Azure | B9: East US
A12: RESUMEN DE COSTOS
A13: Concepto | B13: USD | C13: Detalle
A14: TUs (Throughput Units) | B14: ='Costos Mensuales'!D15 -> 4082.4 | C14: Costo de capacidad de procesamiento
A15: Eventos de ingesta adicionales | B15: ='Costos Mensuales'!D16 -> 357.588 | C15: Sobre el primer millón incluido
A16: Retención extendida (6 días) | B16: ='Costos Mensuales'!D17 -> 123.59619 | C16: Días 2-7 de retención
A17: Consumer Groups | B17: ='Costos Mensuales'!D18 -> 0 | C17: Incluidos en nivel Standard
A18: Subtotal mensual | B18: ='Costos Mensuales'!D19 -> 4563.5842 | C18: Sin contingencia
A19: Buffer contingencia (10%) | B19: ='Costos Mensuales'!D20 -> 456.35842 | C19: Margen para variaciones
A20: TOTAL MENSUAL ESTIMADO | B20: ='Costos Mensuales'!D21 -> 5019.9426 | C20: Con contingencia incluida
A21: PROYECCIÓN ANUAL | B21: ='Costos Mensuales'!D22 -> 60239.311 | C21: Total 12 meses
A24: NOTAS Y SUPUESTOS
A25: • Precios basados en Azure East US (marzo 2026). Sujetos a cambios sin previo aviso.
A26: • Nivel Standard soporta hasta 40 TUs y 20 Consumer Groups.
A27: • Retención día 1 incluida; días 2-7 facturados a $0.010/GB/día.
A28: • No incluye Event Hubs Capture (Blob/ADLS). Activar si se requiere persistencia de largo plazo.
A29: • Se recomienda configurar Auto-Inflate para escalar TUs automáticamente en picos.
A30: • El buffer de 10% cubre variaciones en EPS y tamaño de eventos.
A31: • Para >40 TUs considerar escalar a nivel Premium o Dedicated.
