Workbook

Sheet Resumen
A1: Resumen de costos Azure — Comisión Estatal de Aguas de Querétaro
A2: Suscripción #1427074 · East US · precios de lista Azure (pago por uso) al 02-oct-2026 · inventario del 29-sep-2026
A4: Concepto | B4: USD / mes | C4: MXN / mes | D4: % del total
A5: Cómputo (VMs encendidas) | B5: =Calculadora!G20 -> 3036.8 | C5: =B5*Supuestos!$B$7 -> 56180.8 | D5: =IF($B$11=0,0,B5/$B$11) -> 0.55981288
A6: Discos administrados de las VMs | B6: =Calculadora!L20 -> 1471.8423 | C6: =B6*Supuestos!$B$7 -> 27229.082 | D6: =IF($B$11=0,0,B6/$B$11) -> 0.27132384
A7: Respaldo (instancias + almacenamiento) | B7: =Calculadora!N20+Calculadora!O20 -> 545.62752 | C7: =B7*Supuestos!$B$7 -> 10094.109 | D7: =IF($B$11=0,0,B7/$B$11) -> 0.10058262
A8: Red (IPs públicas, Bastion, Front Door) | B8: =SUM(Calculadora!P25:P28) -> 304.55 | C8: =B8*Supuestos!$B$7 -> 5634.175 | D8: =IF($B$11=0,0,B8/$B$11) -> 0.056141666
A9: Almacenamiento, snapshot y discos huérfanos | B9: =Calculadora!P24+Calculadora!P29+Calculadora!P30 -> 21.35 | C9: =B9*Supuestos!$B$7 -> 394.975 | D9: =IF($B$11=0,0,B9/$B$11) -> 0.0039357234
A10: Monitoreo y Key Vault | B10: =SUM(Calculadora!P31:P34) -> 44.5 | C10: =B10*Supuestos!$B$7 -> 823.25 | D10: =IF($B$11=0,0,B10/$B$11) -> 0.0082032643
A11: Total mensual | B11: =SUM(B5:B10) -> 5424.6698 | C11: =B11*Supuestos!$B$7 -> 100356.39 | D11: =SUM(D5:D10) -> 1
A12: Total anual | B12: =B11*12 -> 65096.037 | C12: =B12*Supuestos!$B$7 -> 1204276.7
A13: Tipo de cambio usado (editar en Supuestos): | B13: =Supuestos!$B$7 -> 18.5
A15: Escenario: si se encendieran las 6 VMs desasignadas 24x7
A16: Cómputo adicional por mes (USD) | B16: =SUMPRODUCT((Calculadora!D5:D19="deallocated")*Calculadora!F5:F19)*Supuestos!$B$5-SUMPRODUCT((Calculadora!D5:D19="deallocated")*Calculadora!G5:G19) -> 2546.24 | C16: =B16*Supuestos!$B$7 -> 47105.44
A18: Notas importantes
A19: • Precios de lista públicos en USD. La suscripción es CSP (Ingram Micro); el precio facturado puede variar por márgenes o descuentos del partner.
A20: • No incluye impuestos (IVA), soporte de Microsoft, salida de datos a Internet más allá del supuesto de Front Door, ni licencias SAP/Oracle (BYOL).
A21: • El tipo de disco por VM no viene en el inventario: se supuso Premium SSD donde el tamaño lo admite. Es la principal fuente de variación (ver Calculadora, columna J).
A22: • Las 6 VMs desasignadas (Dev/QA/Prod App+DB) no generan cómputo, pero sí pagan disco y respaldo.
A23: • Las IP públicas Basic se retiraron el 30-sep-2025; se presupuestan como Standard estáticas.
A24: • Ahorros posibles: eliminar 38 discos huérfanos, liberar 2 IPs sin uso, instancias reservadas 1/3 años o Azure Hybrid Benefit para Windows Server.
A25: • Riesgo: TTechGRPPRD0922 no tiene respaldo; se recomienda protegerlo (+$30/mes aprox.).

Sheet Supuestos
A1: Supuestos y precios de referencia — Azure East US (USD, pago por uso)
A2: Celdas azules con fondo amarillo = editables. Precios: API Azure Retail Prices (prices.azure.com), consultada el 02-oct-2026, precio de lista sin descuentos CSP.
A4: GENERAL
A5: Horas por mes | B5: 730 | C5: Estándar de la Calculadora de Azure
A6: Horas/mes encendidas para VMs hoy desasignadas | B6: 0 | C6: 0 = siguen apagadas (solo pagan disco). Poner 730 si se van a encender.
A7: Tipo de cambio MXN por USD | B7: 18.5 | C7: ACTUALIZAR con el tipo de cambio vigente / el de la factura CSP
A8: Incluir discos huérfanos (1 = sí, 0 = no) | B8: 0 | C8: 38 discos / 9,828 GB de restauraciones 2021-2022; recomendación: eliminarlos
A9: GB de discos huérfanos | B9: 9828 | C9: Del inventario
A10: DISCOS ADMINISTRADOS ($/GB-mes, aprox. por tier de 1 TiB)
A11: Premium SSD (P30 1,024 GB = $135.17/mes) | B11: =135.17/1024 -> 0.13200195 | C11: API: skuName 'P30 LRS', eastus
A12: Standard SSD (E30 1,024 GB = $76.80/mes) | B12: =76.8/1024 -> 0.075 | C12: API: skuName 'E30 LRS', eastus. Más transacciones ($0.002 por 10K)
A13: Standard HDD (S30 1,024 GB = $40.96/mes) | B13: =40.96/1024 -> 0.04 | C13: API: skuName 'S30 LRS', eastus. Más transacciones ($0.0005 por 10K)
A14: Transacciones de disco Standard estimadas ($/mes por disco) | B14: 2 | C14: Supuesto: aplica solo a Standard SSD/HDD
A15: RED
A16: IP pública Standard estática ($/hora) | B16: 0.005 | C16: API: 'Standard IPv4 Static Public IP'. Las IP Basic se retiraron el 30-sep-2025
A17: IPs públicas a conservar | B17: 29 | C17: 31 hoy; las 2 sin asociar se pueden liberar
A18: Azure Bastion Basic ($/hora) | B18: 0.19 | C18: API: 'Basic Gateway'
A19: Azure Front Door Standard, cuota base ($/mes por perfil) | B19: 35 | C19: API: 'Standard Base Fees'. Sin tráfico/solicitudes
A20: Perfiles Front Door Standard | B20: 1 | C20: Los 2 clásicos se consolidan en 1 perfil Standard (Classic se retira en 2027)
A21: Tráfico Front Door + salida de datos estimado ($/mes) | B21: 25 | C21: Supuesto; ajustar con métricas reales de tráfico
A22: RESPALDO (Recovery Services vault)
A23: Almacenamiento de respaldo GRS ($/GB-mes) | B23: 0.0448 | C23: API: Backup 'Standard GRS Data Stored'
A24: Factor GB respaldados / GB aprovisionados | B24: 0.6 | C24: Supuesto: discos ~60% ocupados + retención diaria incremental
A25: SNAPSHOT
A26: Snapshot Standard HDD LRS ($/GB-mes) | B26: 0.05 | C26: Precio de lista de referencia (verificar)
A27: Tamaño del snapshot SAPRouter (GB) | B27: 127 | C27: Supuesto: disco de SO de TTechSAP-router
A28: MONITOREO Y OTROS
A29: Log Analytics ingesta ($/GB) | B29: 2.3 | C29: API: 'Analytics Logs Data Ingestion' (primeros 5 GB/mes gratis)
A30: GB/mes ingeridos en Log Analytics | B30: 20 | C30: Supuesto (agentes MMA/OMS en 15 VMs); verificar en el workspace
A31: Alertas, grupos de acción, Network Watcher, dashboard ($/mes) | B31: 5 | C31: Supuesto: 6 alertas de métricas ≈ $0.10 c/u + notificaciones
A32: Key Vault: 5 bóvedas, operaciones + renovación de certificados ($/mes) | B32: 5 | C32: Supuesto: $0.03 por 10K operaciones; $3 por renovación de certificado
A33: Cuentas de almacenamiento: GB totales (diagnóstico + qorderbackups01 + admintransfers) | B33: 500 | C33: Supuesto: VERIFICAR capacidad real en cada cuenta
A34: Precio blob Hot ($/GB-mes, mezcla LRS/RA-GRS) | B34: 0.03 | C34: Referencia: Hot LRS ≈ $0.0208, RA-GRS ≈ $0.046

Sheet Precios VM
A1: Precios de cómputo por hora — East US, pago por uso (USD)
A2: Fuente: https://prices.azure.com/api/retail/prices (armRegionName='eastus', priceType='Consumption'), 02-oct-2026. Windows incluye licencia.
A4: Tamaño | B4: vCPU | C4: RAM (GiB) | D4: Linux $/h | E4: Windows $/h | F4: Nota
A5: Standard_A4_v2 | B5: 4 | C5: 8 | D5: 0.191 | E5: 0.286 | F5: Av2: no admite Premium SSD
A6: Standard_F4s | B6: 4 | C6: 8 | D6: 0.199 | E6: 0.383
A7: Standard_E4as_v4 | B7: 4 | C7: 32 | D7: 0.252 | E7: 0.436
A8: Standard_E8as_v4 | B8: 8 | C8: 64 | D8: 0.504 | E8: 0.872
A9: Standard_DS13_v2 | B9: 8 | C9: 56 | D9: 0.741 | E9: 0.952
A10: Standard_DS12-1_v2 | B10: 1 | C10: 28 | D10: 0.371 | E10: 0.476 | F10: Restringido a 1 vCPU (hardware de DS12 v2, 4 vCPU)
A11: Standard_B4ms | B11: 4 | C11: 16 | D11: 0.166 | E11: =0.166+0.182 -> 0.348 | F11: Serie B: la API publica la licencia Windows aparte ($0.182/h); total = cómputo + licencia

Sheet Calculadora
A1: Calculadora Azure — CEAQ suscripción #1427074 (East US)
A2: Estimación mensual a precio de lista. Las columnas en azul/amarillo se pueden cambiar; todo lo demás se calcula.
A4: VM | B4: Tamaño | C4: SO | D4: Estado | E4: Horas/mes | F4: $/hora | G4: Cómputo $/mes | H4: Discos (SO+datos) | I4: GB | J4: Tipo de disco | K4: $/GB-mes | L4: Discos $/mes | M4: Respaldo (1/0) | N4: Instancia protegida $/mes | O4: Almac. respaldo $/mes | P4: Total VM $/mes
A5: OracleDBsrv | B5: Standard_A4_v2 | C5: Linux | D5: running | E5: =IF(D5="running",Supuestos!$B$5,Supuestos!$B$6) -> 730 | F5: =INDEX('Precios VM'!$D$5:$E$11,MATCH(B5,'Precios VM'!$A$5:$A$11,0),IF(C5="Windows",2,1)) -> 0.191 | G5: =E5*F5 -> 139.43 | H5: 2 | I5: 94 | J5: Standard SSD | K5: =IF(J5="Premium SSD",Supuestos!$B$11,IF(J5="Standard SSD",Supuestos!$B$12,Supuestos!$B$13)) -> 0.075 | L5: =I5*K5+IF(J5="Premium SSD",0,H5*Supuestos!$B$14) -> 11.05 | M5: 1 | N5: =M5*IF(I5<=50,5,IF(I5<=500,10,10*CEILING(I5/500,1))) -> 10 | O5: =M5*I5*Supuestos!$B$24*Supuestos!$B$23 -> 2.52672 | P5: =G5+L5+N5+O5 -> 163.00672
A6: TTechDMS-PRD | B6: Standard_F4s | C6: Windows | D6: running | E6: =IF(D6="running",Supuestos!$B$5,Supuestos!$B$6) -> 730 | F6: =INDEX('Precios VM'!$D$5:$E$11,MATCH(B6,'Precios VM'!$A$5:$A$11,0),IF(C6="Windows",2,1)) -> 0.383 | G6: =E6*F6 -> 279.59 | H6: 2 | I6: 427 | J6: Premium SSD | K6: =IF(J6="Premium SSD",Supuestos!$B$11,IF(J6="Standard SSD",Supuestos!$B$12,Supuestos!$B$13)) -> 0.13200195 | L6: =I6*K6+IF(J6="Premium SSD",0,H6*Supuestos!$B$14) -> 56.364834 | M6: 1 | N6: =M6*IF(I6<=50,5,IF(I6<=500,10,10*CEILING(I6/500,1))) -> 10 | O6: =M6*I6*Supuestos!$B$24*Supuestos!$B$23 -> 11.47776 | P6: =G6+L6+N6+O6 -> 357.43259
A7: TTechDMS-QAS | B7: Standard_A4_v2 | C7: Windows | D7: running | E7: =IF(D7="running",Supuestos!$B$5,Supuestos!$B$6) -> 730 | F7: =INDEX('Precios VM'!$D$5:$E$11,MATCH(B7,'Precios VM'!$A$5:$A$11,0),IF(C7="Windows",2,1)) -> 0.286 | G7: =E7*F7 -> 208.78 | H7: 2 | I7: 427 | J7: Standard SSD | K7: =IF(J7="Premium SSD",Supuestos!$B$11,IF(J7="Standard SSD",Supuestos!$B$12,Supuestos!$B$13)) -> 0.075 | L7: =I7*K7+IF(J7="Premium SSD",0,H7*Supuestos!$B$14) -> 36.025 | M7: 1 | N7: =M7*IF(I7<=50,5,IF(I7<=500,10,10*CEILING(I7/500,1))) -> 10 | O7: =M7*I7*Supuestos!$B$24*Supuestos!$B$23 -> 11.47776 | P7: =G7+L7+N7+O7 -> 266.28276
A8: TTechDev-App-01 | B8: Standard_E4as_v4 | C8: Windows | D8: deallocated | E8: =IF(D8="running",Supuestos!$B$5,Supuestos!$B$6) -> 0 | F8: =INDEX('Precios VM'!$D$5:$E$11,MATCH(B8,'Precios VM'!$A$5:$A$11,0),IF(C8="Windows",2,1)) -> 0.436 | G8: =E8*F8 -> 0 | H8: 2 | I8: 527 | J8: Premium SSD | K8: =IF(J8="Premium SSD",Supuestos!$B$11,IF(J8="Standard SSD",Supuestos!$B$12,Supuestos!$B$13)) -> 0.13200195 | L8: =I8*K8+IF(J8="Premium SSD",0,H8*Supuestos!$B$14) -> 69.565029 | M8: 1 | N8: =M8*IF(I8<=50,5,IF(I8<=500,10,10*CEILING(I8/500,1))) -> 20 | O8: =M8*I8*Supuestos!$B$24*Supuestos!$B$23 -> 14.16576 | P8: =G8+L8+N8+O8 -> 103.73079
A9: TTechDev-DB-01 | B9: Standard_E4as_v4 | C9: Windows | D9: deallocated | E9: =IF(D9="running",Supuestos!$B$5,Supuestos!$B$6) -> 0 | F9: =INDEX('Precios VM'!$D$5:$E$11,MATCH(B9,'Precios VM'!$A$5:$A$11,0),IF(C9="Windows",2,1)) -> 0.436 | G9: =E9*F9 -> 0 | H9: 2 | I9: 1000 | J9: Premium SSD | K9: =IF(J9="Premium SSD",Supuestos!$B$11,IF(J9="Standard SSD",Supuestos!$B$12,Supuestos!$B$13)) -> 0.13200195 | L9: =I9*K9+IF(J9="Premium SSD",0,H9*Supuestos!$B$14) -> 132.00195 | M9: 1 | N9: =M9*IF(I9<=50,5,IF(I9<=500,10,10*CEILING(I9/500,1))) -> 20 | O9: =M9*I9*Supuestos!$B$24*Supuestos!$B$23 -> 26.88 | P9: =G9+L9+N9+O9 -> 178.88195
A10: TTechGRP-PRD | B10: Standard_DS13_v2 | C10: Windows | D10: running | E10: =IF(D10="running",Supuestos!$B$5,Supuestos!$B$6) -> 730 | F10: =INDEX('Precios VM'!$D$5:$E$11,MATCH(B10,'Precios VM'!$A$5:$A$11,0),IF(C10="Windows",2,1)) -> 0.952 | G10: =E10*F10 -> 694.96 | H10: 7 | I10: 1275 | J10: Premium SSD | K10: =IF(J10="Premium SSD",Supuestos!$B$11,IF(J10="Standard SSD",Supuestos!$B$12,Supuestos!$B$13)) -> 0.13200195 | L10: =I10*K10+IF(J10="Premium SSD",0,H10*Supuestos!$B$14) -> 168.30249 | M10: 1 | N10: =M10*IF(I10<=50,5,IF(I10<=500,10,10*CEILING(I10/500,1))) -> 30 | O10: =M10*I10*Supuestos!$B$24*Supuestos!$B$23 -> 34.272 | P10: =G10+L10+N10+O10 -> 927.53449
A11: TTechGRP-QAS | B11: Standard_DS12-1_v2 | C11: Windows | D11: running | E11: =IF(D11="running",Supuestos!$B$5,Supuestos!$B$6) -> 730 | F11: =INDEX('Precios VM'!$D$5:$E$11,MATCH(B11,'Precios VM'!$A$5:$A$11,0),IF(C11="Windows",2,1)) -> 0.476 | G11: =E11*F11 -> 347.48 | H11: 6 | I11: 975 | J11: Premium SSD | K11: =IF(J11="Premium SSD",Supuestos!$B$11,IF(J11="Standard SSD",Supuestos!$B$12,Supuestos!$B$13)) -> 0.13200195 | L11: =I11*K11+IF(J11="Premium SSD",0,H11*Supuestos!$B$14) -> 128.7019 | M11: 1 | N11: =M11*IF(I11<=50,5,IF(I11<=500,10,10*CEILING(I11/500,1))) -> 20 | O11: =M11*I11*Supuestos!$B$24*Supuestos!$B$23 -> 26.208 | P11: =G11+L11+N11+O11 -> 522.3899
A12: TTechGRPPRD0922 | B12: Standard_DS13_v2 | C12: Windows | D12: running | E12: =IF(D12="running",Supuestos!$B$5,Supuestos!$B$6) -> 730 | F12: =INDEX('Precios VM'!$D$5:$E$11,MATCH(B12,'Precios VM'!$A$5:$A$11,0),IF(C12="Windows",2,1)) -> 0.952 | G12: =E12*F12 -> 694.96 | H12: 7 | I12: 1275 | J12: Premium SSD | K12: =IF(J12="Premium SSD",Supuestos!$B$11,IF(J12="Standard SSD",Supuestos!$B$12,Supuestos!$B$13)) -> 0.13200195 | L12: =I12*K12+IF(J12="Premium SSD",0,H12*Supuestos!$B$14) -> 168.30249 | M12: 0 | N12: =M12*IF(I12<=50,5,IF(I12<=500,10,10*CEILING(I12/500,1))) -> 0 | O12: =M12*I12*Supuestos!$B$24*Supuestos!$B$23 -> 0 | P12: =G12+L12+N12+O12 -> 863.26249
A13: TTechProd-App-1 | B13: Standard_E8as_v4 | C13: Windows | D13: deallocated | E13: =IF(D13="running",Supuestos!$B$5,Supuestos!$B$6) -> 0 | F13: =INDEX('Precios VM'!$D$5:$E$11,MATCH(B13,'Precios VM'!$A$5:$A$11,0),IF(C13="Windows",2,1)) -> 0.872 | G13: =E13*F13 -> 0 | H13: 2 | I13: 627 | J13: Premium SSD | K13: =IF(J13="Premium SSD",Supuestos!$B$11,IF(J13="Standard SSD",Supuestos!$B$12,Supuestos!$B$13)) -> 0.13200195 | L13: =I13*K13+IF(J13="Premium SSD",0,H13*Supuestos!$B$14) -> 82.765225 | M13: 1 | N13: =M13*IF(I13<=50,5,IF(I13<=500,10,10*CEILING(I13/500,1))) -> 20 | O13: =M13*I13*Supuestos!$B$24*Supuestos!$B$23 -> 16.85376 | P13: =G13+L13+N13+O13 -> 119.61898
A14: TTechProd-DB-01 | B14: Standard_E8as_v4 | C14: Windows | D14: deallocated | E14: =IF(D14="running",Supuestos!$B$5,Supuestos!$B$6) -> 0 | F14: =INDEX('Precios VM'!$D$5:$E$11,MATCH(B14,'Precios VM'!$A$5:$A$11,0),IF(C14="Windows",2,1)) -> 0.872 | G14: =E14*F14 -> 0 | H14: 3 | I14: 2163 | J14: Premium SSD | K14: =IF(J14="Premium SSD",Supuestos!$B$11,IF(J14="Standard SSD",Supuestos!$B$12,Supuestos!$B$13)) -> 0.13200195 | L14: =I14*K14+IF(J14="Premium SSD",0,H14*Supuestos!$B$14) -> 285.52022 | M14: 1 | N14: =M14*IF(I14<=50,5,IF(I14<=500,10,10*CEILING(I14/500,1))) -> 50 | O14: =M14*I14*Supuestos!$B$24*Supuestos!$B$23 -> 58.14144 | P14: =G14+L14+N14+O14 -> 393.66166
A15: TTechQA-App-01 | B15: Standard_E4as_v4 | C15: Windows | D15: deallocated | E15: =IF(D15="running",Supuestos!$B$5,Supuestos!$B$6) -> 0 | F15: =INDEX('Precios VM'!$D$5:$E$11,MATCH(B15,'Precios VM'!$A$5:$A$11,0),IF(C15="Windows",2,1)) -> 0.436 | G15: =E15*F15 -> 0 | H15: 2 | I15: 277 | J15: Premium SSD | K15: =IF(J15="Premium SSD",Supuestos!$B$11,IF(J15="Standard SSD",Supuestos!$B$12,Supuestos!$B$13)) -> 0.13200195 | L15: =I15*K15+IF(J15="Premium SSD",0,H15*Supuestos!$B$14) -> 36.564541 | M15: 1 | N15: =M15*IF(I15<=50,5,IF(I15<=500,10,10*CEILING(I15/500,1))) -> 10 | O15: =M15*I15*Supuestos!$B$24*Supuestos!$B$23 -> 7.44576 | P15: =G15+L15+N15+O15 -> 54.010301
A16: TTechQA-DB-01 | B16: Standard_E4as_v4 | C16: Windows | D16: deallocated | E16: =IF(D16="running",Supuestos!$B$5,Supuestos!$B$6) -> 0 | F16: =INDEX('Precios VM'!$D$5:$E$11,MATCH(B16,'Precios VM'!$A$5:$A$11,0),IF(C16="Windows",2,1)) -> 0.436 | G16: =E16*F16 -> 0 | H16: 2 | I16: 727 | J16: Premium SSD | K16: =IF(J16="Premium SSD",Supuestos!$B$11,IF(J16="Standard SSD",Supuestos!$B$12,Supuestos!$B$13)) -> 0.13200195 | L16: =I16*K16+IF(J16="Premium SSD",0,H16*Supuestos!$B$14) -> 95.96542 | M16: 1 | N16: =M16*IF(I16<=50,5,IF(I16<=500,10,10*CEILING(I16/500,1))) -> 20 | O16: =M16*I16*Supuestos!$B$24*Supuestos!$B$23 -> 19.54176 | P16: =G16+L16+N16+O16 -> 135.50718
... A19: TTechSAP-router | B19: Standard_A4_v2 | C19: Windows | D19: running | E19: =IF(D19="running",Supuestos!$B$5,Supuestos!$B$6) -> 730 | F19: =INDEX('Precios VM'!$D$5:$E$11,MATCH(B19,'Precios VM'!$A$5:$A$11,0),IF(C19="Windows",2,1)) -> 0.286 | G19: =E19*F19 -> 208.78 | H19: 2 | I19: 210 | J19: Standard SSD | K19: =IF(J19="Premium SSD",Supuestos!$B$11,IF(J19="Standard SSD",Supuestos!$B$12,Supuestos!$B$13)) -> 0.075 | L19: =I19*K19+IF(J19="Premium SSD",0,H19*Supuestos!$B$14) -> 19.75 | M19: 1 | N19: =M19*IF(I19<=50,5,IF(I19<=500,10,10*CEILING(I19/500,1))) -> 10 | O19: =M19*I19*Supuestos!$B$24*Supuestos!$B$23 -> 5.6448 | P19: =G19+L19+N19+O19 -> 244.1748
A20: Subtotal máquinas virtuales | E20: =SUM(E5:E19) -> 6570 | G20: =SUM(G5:G19) -> 3036.8 | H20: =SUM(H5:H19) -> 49 | I20: =SUM(I5:I19) -> 11529 | L20: =SUM(L5:L19) -> 1471.8423 | N20: =SUM(N5:N19) -> 270 | O20: =SUM(O5:O19) -> 275.62752 | P20: =SUM(P5:P19) -> 5054.2698
A22: Otros servicios
A23: Servicio | B23: Detalle | E23: Cantidad | F23: Precio unitario | G23: Unidad | P23: $/mes
A24: Discos huérfanos | B24: Restauraciones 2021-2022 como Standard HDD (solo si se conservan) | E24: =Supuestos!$B$9*Supuestos!$B$8 -> 0 | F24: =Supuestos!$B$13 -> 0.04 | G24: GB-mes | P24: =E24*F24 -> 0
A25: IPs públicas | B25: Standard estáticas (las Basic ya no existen) | E25: =Supuestos!$B$17 -> 29 | F25: =Supuestos!$B$16*Supuestos!$B$5 -> 3.65 | G25: IP-mes | P25: =E25*F25 -> 105.85
A26: Azure Bastion | B26: Qorder-bastion, SKU Basic | E26: 1 | F26: =Supuestos!$B$18*Supuestos!$B$5 -> 138.7 | G26: instancia-mes | P26: =E26*F26 -> 138.7
A27: Azure Front Door | B27: Perfil Standard (cuota base) | E27: =Supuestos!$B$20 -> 1 | F27: =Supuestos!$B$19 -> 35 | G27: perfil-mes | P27: =E27*F27 -> 35
A28: Front Door tráfico / salida de datos | B28: Estimado | E28: 1 | F28: =Supuestos!$B$21 -> 25 | G28: global | P28: =E28*F28 -> 25
A29: Snapshot | B29: SAPRouter-previoamovimientoregistro | E29: =Supuestos!$B$27 -> 127 | F29: =Supuestos!$B$26 -> 0.05 | G29: GB-mes | P29: =E29*F29 -> 6.35
A30: Cuentas de almacenamiento | B30: 15 cuentas (diagnóstico, respaldos, transferencias) | E30: =Supuestos!$B$33 -> 500 | F30: =Supuestos!$B$34 -> 0.03 | G30: GB-mes | P30: =E30*F30 -> 15
A31: Log Analytics | B31: Ingesta de agentes MMA/OMS y Dependency Agent (5 GB gratis) | E31: =MAX(0,Supuestos!$B$30-5) -> 15 | F31: =Supuestos!$B$29 -> 2.3 | G31: GB | P31: =E31*F31 -> 34.5
A32: Monitor | B32: 6 alertas de métricas, 2 de actividad, 3 grupos de acción | E32: 1 | F32: =Supuestos!$B$31 -> 5 | G32: global | P32: =E32*F32 -> 5
A33: Key Vault | B33: 5 bóvedas (certificados SSL) | E33: 1 | F33: =Supuestos!$B$32 -> 5 | G33: global | P33: =E33*F33 -> 5
A34: VNets, NSG, NICs, Network Watcher, AVD workspace | B34: Sin costo directo | E34: 0 | F34: 0 | G34: - | P34: =E34*F34 -> 0
A35: Subtotal otros servicios | P35: =SUM(P24:P34) -> 370.4
M37: TOTAL MENSUAL (USD) | P37: =P20+P35 -> 5424.6698
M38: TOTAL MENSUAL (MXN) | P38: =P37*Supuestos!$B$7 -> 100356.39
M39: TOTAL ANUAL (USD) | P39: =P37*12 -> 65096.037
M40: TOTAL ANUAL (MXN) | P40: =P39*Supuestos!$B$7 -> 1204276.7
