Workbook

Sheet Resumen
B2: Estimado de Costos Azure — Ambiente SAP S/4HANA (Instalacion Inicial)
B3: Region: East US | Moneda: USD | Fecha de referencia: 29-jul-2026
B4: Cifras de referencia para planeacion. Validar montos finales en la Azure Pricing Calculator antes de aprobar presupuesto.
B6: Escenario | C6: Computo mensual ($) | D6: Storage mensual ($) | E6: Total mensual ($) | F6: Total anual ($)
B7: Pay-as-you-go | C7: =VMs!L8 -> 6186.75 | D7: =Discos!J11 -> 519.4636 | E7: =C7+D7 -> 6706.2136 | F7: =E7*12 -> 80474.563
B8: Reservado 1 año | C8: =VMs!M8 -> 3642.7 | D8: =Discos!J11 -> 519.4636 | E8: =C8+D8 -> 4162.1636 | F8: =E8*12 -> 49945.963
B9: Reservado 3 años | C9: =VMs!N8 -> 1901.504 | D9: =Discos!J11 -> 519.4636 | E9: =C9+D9 -> 2420.9676 | F9: =E9*12 -> 29051.611
B12: Nota: Storage se asume constante entre escenarios de computo (los discos no tienen descuento por reserva de instancia).

Sheet VMs
B2: Detalle de Maquinas Virtuales (Compute)
B3: Editar en azul: Cantidad y Horas/mes. Tarifas Linux, sin licencia SO, East US.
B5: Rol SAP | C5: Equivalente AWS | D5: SKU Azure | E5: vCPU | F5: RAM (GiB) | G5: Cantidad | H5: Horas/mes | I5: Tarifa PAYG ($/hr) | J5: Tarifa Reserv. 1a ($/hr) | K5: Tarifa Reserv. 3a ($/hr) | L5: Costo mensual PAYG ($) | M5: Costo mensual 1a ($) | N5: Costo mensual 3a ($)
B6: DB/App S/4HANA (inicial) | C6: R6i.8xlarge | D6: Standard_E32s_v5 | E6: 32 | F6: 256 | G6: 1 | H6: 730 | I6: 2.016 | J6: 1.2438 | K6: 0.7963 | L6: =G6*H6*I6 -> 1471.68 | M6: =G6*H6*J6 -> 907.974 | N6: =G6*H6*K6 -> 581.299
B7: DB HANA alta memoria (opcional) | C7: X1.16xlarge | D7: Standard_M64s_v2 | E7: 64 | F7: 1024 | G7: 1 | H7: 730 | I7: 6.459 | J7: 3.7462 | K7: 1.8085 | L7: =G7*H7*I7 -> 4715.07 | M7: =G7*H7*J7 -> 2734.726 | N7: =G7*H7*K7 -> 1320.205
B8: Total Compute | L8: =SUM(L6:L7) -> 6186.75 | M8: =SUM(M6:M7) -> 3642.7 | N8: =SUM(N6:N7) -> 1901.504

Sheet Discos
B2: Detalle de Almacenamiento (Discos y Share)
B3: Editar en azul: Tamano (GiB), IOPS extra y Throughput extra. East US.
B5: Recurso SAP | C5: Tipo Azure | D5: Tamano (GiB) | E5: $/GiB-mes | F5: IOPS extra sobre base | G5: $/IOPS-mes | H5: MBps extra sobre base | I5: $/MBps-mes | J5: Costo mensual ($)
B6: OS Disk x2 (DB + HANA-mem) | C6: Premium SSD P10 (128 GiB c/u) x2 | D6: 256 | E6: 0.1541 | F6: 0 | G6: 0 | H6: 0 | I6: 0 | J6: =(D6*E6)+(F6*G6)+(H6*I6) -> 39.4496
B7: Data HANA (Data1) | C7: Premium SSD v2 | D7: 1200 | E7: 0.081 | F7: 2000 | G7: 0.0052 | H7: 125 | I7: 0.041 | J7: =(D7*E7)+(F7*G7)+(H7*I7) -> 112.725
B8: Log HANA (Write Accelerator) | C8: Premium SSD v2 | D8: 500 | E8: 0.081 | F8: 2000 | G8: 0.0052 | H8: 125 | I8: 0.041 | J8: =(D8*E8)+(F8*G8)+(H8*I8) -> 56.025
B9: App SAP (binarios) | C9: Premium SSD P6 (64 GiB) | D9: 64 | E9: 0.1595 | F9: 0 | G9: 0 | H9: 0 | I9: 0 | J9: =(D9*E9)+(F9*G9)+(H9*I9) -> 10.208
B10: Share (/sapmnt, /trans) | C10: Azure NetApp Files - Premium | D10: 1024 | E10: 0.294 | F10: 0 | G10: 0 | H10: 0 | I10: 0 | J10: =(D10*E10)+(F10*G10)+(H10*I10) -> 301.056
B11: Total Storage | J11: =SUM(J6:J10) -> 519.4636

Sheet Notas y Supuestos
B2: Notas, Fuentes y Supuestos
B4: Region: East US. Precios en USD, sistema operativo Linux (sin licencia incluida), sin Azure Hybrid Benefit.
B6: COMPUTO:
B7: - Standard_E32s_v5 (32 vCPU / 256 GiB): PAYG $2.0160/hr, Reservado 1a $1.2438/hr, Reservado 3a $0.7963/hr. Fuente: tarifas publicas Azure (Holori/CloudPrice), consultado 29-jul-2026.
B8: - Standard_M64s_v2 (64 vCPU / 1024 GiB): PAYG estimado $6.4590/hr (CloudPrice, $4,715.07/mes / 730 hrs). Tarifas Reservado 1a y 3a NO estan publicadas para esta SKU especifica en las fuentes consultadas; se estimaron aplicando el mismo % de descuento observado en Standard_M64s (v1): ~42% (1a) y ~72% (3a). VALIDAR este dato puntual en la Azure Pricing Calculator o Retail Prices API antes de usarlo en un presupuesto formal.
B9: - 730 horas/mes asume operacion 24x7. Ajustar la columna 'Horas/mes' si el ambiente se apaga fuera de horario (ej. Dev/QA).
B11: ALMACENAMIENTO:
B12: - Premium SSD v2 (Data y Log de HANA): $0.0810/GiB-mes de capacidad; primeros 3,000 IOPS y 125 MBps incluidos sin costo; excedente a $0.0052/IOPS-mes y $0.0410/MBps-mes. Se asumieron 5,000 IOPS y 250 MBps provisionados por disco (2,000 IOPS y 125 MBps de excedente) como punto de partida — ajustar segun el sizing real de HANA.
B13: - OS Disk: Premium SSD P10 (128 GiB) ~$19.71/mes cada uno; se muestran 2 discos (uno por VM) a tarifa combinada.
B14: - App SAP: Premium SSD P6 (64 GiB) ~$10.21/mes (se redondea el disco de 50 GiB solicitado al tier P6).
B15: - Share (/sapmnt, /trans): estimado con Azure NetApp Files tier Premium (~$0.294/GiB-mes). Alternativa mas economica: tier Standard (~$0.152/GiB-mes) si el I/O requerido es menor.
B16: - El log de HANA en la solicitud original aparece como '0.5 GB'; se asumio que se referia a 500 GiB (0.5 TB) dado que un log de 0.5 GB es atipicamente pequeno para HANA productivo. Confirmar el tamano real con el equipo de Basis/sizing.
... B27: 3. Para una cotizacion con descuentos negociados (Enterprise Agreement / MACC), contactar al representante de cuenta de Microsoft o CSP.
